alibabacloud_ims_editing_mcp_server/__init__.py
alibabacloud_ims_editing_mcp_server/client.py
alibabacloud_ims_editing_mcp_server/mcp_server.py
alibabacloud_ims_editing_mcp_server/tools/__init__.py
alibabacloud_ims_editing_mcp_server/tools/editing_tools.py
alibabacloud_ims_editing_mcp_server/tools/media_comprehension_tools.py
alibabacloud_ims_editing_mcp_server/tools/media_tools.py
alibabacloud_ims_editing_mcp_server/tools/param_type.py
alibabacloud_ims_editing_mcp_server/tools/subscription_tools.py
alibabacloud_ims_editing_mcp_server/tools/tool_registration.py
alibabacloud_ims_editing_mcp_server-0.0.3.dist-info/licenses/LICENSE
alibabacloud_ims_editing_mcp_server-0.0.3.dist-info/METADATA
alibabacloud_ims_editing_mcp_server-0.0.3.dist-info/WHEEL
alibabacloud_ims_editing_mcp_server-0.0.3.dist-info/entry_points.txt
alibabacloud_ims_editing_mcp_server-0.0.3.dist-info/top_level.txt
alibabacloud_ims_editing_mcp_server-0.0.3.dist-info/RECORD
