Metadata-Version: 2.4
Name: alibabacloud-ims-editing-mcp-server
Version: 0.0.3
Summary: IMS Editing MCP Server
License-Expression: Apache-2.0
Requires-Python: >=3.12
License-File: LICENSE
Requires-Dist: alibabacloud-ice20201109==6.4.2
Requires-Dist: fastmcp==2.8.0
Requires-Dist: python-dotenv>=1.1.0
Requires-Dist: alibabacloud_oss_v2>=1.1.0
Dynamic: license-file
